ndsplines/__init__.py
ndsplines/_bspl.c
ndsplines/_bspl.cp313-win_amd64.pyd
ndsplines/_bspl.h
ndsplines/_bspl.pyx
ndsplines/ndsplines.py
ndsplines/version.py
ndsplines-0.3.0.dist-info/licenses/LICENSE
ndsplines-0.3.0.dist-info/METADATA
ndsplines-0.3.0.dist-info/WHEEL
ndsplines-0.3.0.dist-info/top_level.txt
ndsplines-0.3.0.dist-info/RECORD
