Metadata-Version: 2.4
Name: ndsplines
Version: 0.3.0
Summary: Multi-dimensional splines
Author-email: Benjamin Margolis <ben@sixpearls.com>
Maintainer-email: Kenneth Lyons <ixjlyons@gmail.com>
License-Expression: BSD-3-Clause
Classifier: Programming Language :: Python :: 3
Classifier: Programming Language :: Python :: 3.9
Classifier: Programming Language :: Python :: 3.10
Classifier: Programming Language :: Python :: 3.11
Classifier: Programming Language :: Python :: 3.12
Classifier: Programming Language :: Python :: 3.13
Requires-Python: >=3.9
License-File: LICENSE
Requires-Dist: numpy
Requires-Dist: scipy
Provides-Extra: test
Requires-Dist: pytest; extra == "test"
Requires-Dist: pandas; extra == "test"
Provides-Extra: docs
Requires-Dist: sphinx; extra == "docs"
Requires-Dist: sphinx_gallery; extra == "docs"
Requires-Dist: matplotlib; extra == "docs"
Requires-Dist: pandas; extra == "docs"
Provides-Extra: examples
Requires-Dist: matplotlib; extra == "examples"
Requires-Dist: pandas; extra == "examples"
Dynamic: license-file
